optobench
