Metadata-Version: 2.1
Name: optobench
Version: 0.2.2
Summary: Benchmark Functions for Optimization
Home-page: https://github.com/kvoss/optobench
Author: K. Voss
Author-email: k.voss@usask.ca
License: BSD 3-Clause License
Download-URL: https://github.com/kvoss/optobench/releases
Keywords: optimization benchmark
Platform: Windows
Platform: Linux
Platform: Solaris
Platform: Mac OS-X
Platform: Unix
Classifier: Development Status :: 2 - Pre-Alpha
Classifier: Intended Audience :: Developers
Classifier: Intended Audience :: Education
Classifier: Intended Audience :: Science/Research
Classifier: License :: OSI Approved :: BSD License
Classifier: Programming Language :: C++
Classifier: Programming Language :: Python
Classifier: Programming Language :: Python :: 3
Classifier: Programming Language :: Python :: 3.6
Classifier: Programming Language :: Python :: 3.7
Classifier: Programming Language :: Python :: 3.8
Classifier: Programming Language :: Python :: 3.9
Classifier: Topic :: Software Development :: Libraries
Classifier: Topic :: Scientific/Engineering
Classifier: Topic :: Scientific/Engineering :: Artificial Intelligence
Classifier: Topic :: Scientific/Engineering :: Mathematics
Classifier: Operating System :: Microsoft :: Windows
Classifier: Operating System :: POSIX
Classifier: Operating System :: POSIX :: Linux
Classifier: Operating System :: Unix
Classifier: Operating System :: MacOS
Requires-Python: >=3.6
License-File: LICENSE
